setup.py
AutoTool.egg-info/PKG-INFO
AutoTool.egg-info/SOURCES.txt
AutoTool.egg-info/dependency_links.txt
AutoTool.egg-info/not-zip-safe
AutoTool.egg-info/requires.txt
AutoTool.egg-info/top_level.txt
config/__init__.py
config/config.py
msr/__init__.py
msr/msr.py
scr/__init__.py
scr/scr.py