Metadata-Version: 1.1
Name: AutoTool
Version: 0.1
Summary: Automatisation package
Home-page: UNKNOWN
Author: Simatov A.V.
Author-email: vadim.simatov2016@yandex.ru
License: UNKNOWN
Keywords: spectrum analyzer remote control
Platform: UNKNOWN
Classifier: Development Status :: 3 - Alpha
Classifier: License :: OSI Approved :: MIT License
Classifier: Programming Language :: Python :: 3.0
Classifier: Topic :: Text Processing :: Linguistic
